README
setup.py
./LICENSE
./README
./requirements.txt
./sisqo/__init__.py
./sisqo/configuration.py
./sisqo/ssh.py
sisqo.egg-info/PKG-INFO
sisqo.egg-info/SOURCES.txt
sisqo.egg-info/dependency_links.txt
sisqo.egg-info/requires.txt
sisqo.egg-info/top_level.txt