Metadata-Version: 1.1
Name: sisqo
Version: 2.0.11
Summary: A better library for automating network gear with Cisco-style command line interfaces
Home-page: https://github.com/AlexForster/sisqo
Author: Alex Forster
Author-email: alex@alexforster.com
License: 3-Clause ("New") BSD license
Download-URL: https://pypi.python.org/pypi/sisqo
Platform: UNKNOWN
Classifier: Development Status :: 5 - Production/Stable
Classifier: Intended Audience :: Developers
Classifier: License :: OSI Approved :: BSD License
Classifier: Operating System :: MacOS :: MacOS X
Classifier: Operating System :: POSIX
Classifier: Operating System :: POSIX :: BSD
Classifier: Operating System :: POSIX :: Linux
Classifier: Programming Language :: Python
Classifier: Topic :: Software Development :: Libraries
